jupyterlab_chat/__init__.py
jupyterlab_chat/_version.py
jupyterlab_chat/models.py
jupyterlab_chat/py.typed
jupyterlab_chat/ychat.py
jupyterlab_chat/tests/__init__.py
jupyterlab_chat/tests/test_ychat.py
jupyterlab_chat-0.18.2.data/data/etc/jupyter/jupyter_server_config.d/jupyterlab_chat.json
jupyterlab_chat-0.18.2.data/data/share/jupyter/labextensions/jupyterlab-chat-extension/package.json
jupyterlab_chat-0.18.2.data/data/share/jupyter/labextensions/jupyterlab-chat-extension/schemas/jupyterlab-chat-extension/chat-panel.json
jupyterlab_chat-0.18.2.data/data/share/jupyter/labextensions/jupyterlab-chat-extension/schemas/jupyterlab-chat-extension/commands.json
jupyterlab_chat-0.18.2.data/data/share/jupyter/labextensions/jupyterlab-chat-extension/schemas/jupyterlab-chat-extension/factory.json
jupyterlab_chat-0.18.2.data/data/share/jupyter/labextensions/jupyterlab-chat-extension/schemas/jupyterlab-chat-extension/package.json.orig
jupyterlab_chat-0.18.2.data/data/share/jupyter/labextensions/jupyterlab-chat-extension/static/359.3a6afca5fc7be05afda7.js
jupyterlab_chat-0.18.2.data/data/share/jupyter/labextensions/jupyterlab-chat-extension/static/432.d2a5c1fd7adebf3d588e.js
jupyterlab_chat-0.18.2.data/data/share/jupyter/labextensions/jupyterlab-chat-extension/static/488.9c69b0120a3482fb78b2.js
jupyterlab_chat-0.18.2.data/data/share/jupyter/labextensions/jupyterlab-chat-extension/static/515.885a8e93a5b90aa30b8b.js
jupyterlab_chat-0.18.2.data/data/share/jupyter/labextensions/jupyterlab-chat-extension/static/800.a8891f49d08b8da65b95.js
jupyterlab_chat-0.18.2.data/data/share/jupyter/labextensions/jupyterlab-chat-extension/static/800.a8891f49d08b8da65b95.js.LICENSE.txt
jupyterlab_chat-0.18.2.data/data/share/jupyter/labextensions/jupyterlab-chat-extension/static/823.bb328c185f8e4e656382.js
jupyterlab_chat-0.18.2.data/data/share/jupyter/labextensions/jupyterlab-chat-extension/static/remoteEntry.05c89d2a6e87ce988783.js
jupyterlab_chat-0.18.2.dist-info/METADATA
jupyterlab_chat-0.18.2.dist-info/WHEEL
jupyterlab_chat-0.18.2.dist-info/entry_points.txt
jupyterlab_chat-0.18.2.dist-info/licenses/LICENSE
jupyterlab_chat-0.18.2.dist-info/RECORD
