Metadata-Version: 2.4
Name: jupyterlab_chat
Version: 0.18.2
Summary: A chat extension based on shared documents
Project-URL: documentation, https://jupyter-chat.readthedocs.io/
Project-URL: homepage, https://github.com/jupyterlab/jupyter-chat
Project-URL: Bug Tracker, https://github.com/jupyterlab/jupyter-chat/issues
Author-email: Jupyter Development Team <jupyter@googlegroups.com>
License: BSD 3-Clause License
License-File: LICENSE
Keywords: jupyter,jupyterlab,jupyterlab-extension
Classifier: Framework :: Jupyter
Classifier: Framework :: Jupyter :: JupyterLab
Classifier: Framework :: Jupyter :: JupyterLab :: 4
Classifier: Framework :: Jupyter :: JupyterLab :: Extensions
Classifier: Framework :: Jupyter :: JupyterLab :: Extensions :: Prebuilt
Classifier: License :: OSI Approved :: BSD License
Classifier: Programming Language :: Python
Classifier: Programming Language :: Python :: 3
Classifier: Programming Language :: Python :: 3.9
Classifier: Programming Language :: Python :: 3.10
Classifier: Programming Language :: Python :: 3.11
Classifier: Programming Language :: Python :: 3.12
Classifier: Programming Language :: Python :: 3.13
Requires-Python: >=3.9
Requires-Dist: jupyter-collaboration<5,>=4
Requires-Dist: jupyter-server<3,>=2.0.1
Requires-Dist: jupyter-ydoc<4.0.0,>=3.0.0
Requires-Dist: pycrdt<0.13.0,>=0.12.0
Provides-Extra: test
Requires-Dist: coverage; extra == 'test'
Requires-Dist: mypy; extra == 'test'
Requires-Dist: pytest; extra == 'test'
Requires-Dist: pytest-asyncio; extra == 'test'
Requires-Dist: pytest-cov; extra == 'test'
Requires-Dist: pytest-jupyter[server]>=0.6.0; extra == 'test'
